LICENSE.txt
MANIFEST.in
README.rst
setup.py
cmsplugin_mathjax/__init__.py
cmsplugin_mathjax/cms_plugins.py
cmsplugin_mathjax/models.py
cmsplugin_mathjax/settings.py
cmsplugin_mathjax.egg-info/PKG-INFO
cmsplugin_mathjax.egg-info/SOURCES.txt
cmsplugin_mathjax.egg-info/dependency_links.txt
cmsplugin_mathjax.egg-info/not-zip-safe
cmsplugin_mathjax.egg-info/requires.txt
cmsplugin_mathjax.egg-info/top_level.txt
cmsplugin_mathjax/migrations/0001_initial.py
cmsplugin_mathjax/migrations/0002_auto_20161021_2213.py
cmsplugin_mathjax/migrations/0003_auto_20161021_2222.py
cmsplugin_mathjax/migrations/__init__.py
cmsplugin_mathjax/templates/cmsplugin_mathjax/plugin.html